lambda_lift/__init__.py
lambda_lift/cli.py
py_lambda_lift-1.0.0rc5.dist-info/METADATA
py_lambda_lift-1.0.0rc5.dist-info/WHEEL
py_lambda_lift-1.0.0rc5.dist-info/entry_points.txt
py_lambda_lift-1.0.0rc5.dist-info/top_level.txt
py_lambda_lift-1.0.0rc5.dist-info/RECORD
