Metadata-Version: 2.4
Name: py-lambda-lift
Version: 1.0.0rc5
Summary: A utility to streamline AWS Lambda function deployments
Home-page: https://github.com/marnautoupages/lambda-lift
Author: Marwan Eddabaa
Author-email: 
License-Expression: MIT
Project-URL: Homepage, https://github.com/marnautoupages/lambda-lift
Project-URL: Bug Reports, https://github.com/marnautoupages/lambda-lift/issues
Project-URL: Source, https://github.com/marnautoupages/lambda-lift
Keywords: aws,lambda,deployment,serverless,cli
Classifier: Development Status :: 4 - Beta
Classifier: Intended Audience :: Developers
Classifier: Topic :: Software Development :: Build Tools
Classifier: Programming Language :: Python :: 3
Classifier: Programming Language :: Python :: 3.8
Classifier: Programming Language :: Python :: 3.9
Classifier: Programming Language :: Python :: 3.10
Classifier: Programming Language :: Python :: 3.11
Classifier: Programming Language :: Python :: 3.12
Requires-Python: >=3.8
Dynamic: home-page
Dynamic: requires-python
